openfeature/contrib/provider/flipt/__init__.py
openfeature_provider_flipt-0.1.3.dist-info/METADATA
openfeature_provider_flipt-0.1.3.dist-info/WHEEL
openfeature_provider_flipt-0.1.3.dist-info/licenses/LICENSE
openfeature_provider_flipt-0.1.3.dist-info/RECORD
