Metadata-Version: 2.4
Name: openfeature-provider-flipt
Version: 0.1.3
Summary: OpenFeature provider for the Flipt feature flagging service
Project-URL: Homepage, https://github.com/open-feature/python-sdk-contrib
Author-email: OpenFeature <openfeature-core@groups.io>
License:                                  Apache License
License-File: LICENSE
Classifier: License :: OSI Approved :: Apache Software License
Classifier: Programming Language :: Python
Classifier: Programming Language :: Python :: 3
Requires-Python: >=3.8
Requires-Dist: openfeature-provider-ofrep>=0.1.0
Requires-Dist: openfeature-sdk>=0.7.0
